benchmarking/__init__.py
benchmarking/benchmark.py
benchmarking/utils/__init__.py
benchmarking/utils/graphs.py
benchmarking/utils/heapq.py
benchmarking/utils/sc_dijkstra.py
benchmarking/utils/time_case.py
benchmarking/utils/vanilla_dijkstra.py
bmsspy/__init__.py
bmsspy/core.py
bmsspy/entrypoint.py
bmsspy/data_structures/__init__.py
bmsspy/data_structures/data_structure.py
bmsspy/data_structures/heap_data_structure.py
bmsspy/data_structures/list_data_structure.py
bmsspy/data_structures/unique_data_structure.py
bmsspy/helpers/__init__.py
bmsspy/helpers/fast.py
bmsspy/helpers/heapdict.py
bmsspy/helpers/quicksplit.py
bmsspy/helpers/rbtree.py
bmsspy/helpers/utils.py
bmsspy-2.1.1.dist-info/licenses/LICENSE
bmsspy-2.1.1.dist-info/METADATA
bmsspy-2.1.1.dist-info/WHEEL
bmsspy-2.1.1.dist-info/top_level.txt
bmsspy-2.1.1.dist-info/RECORD
