Metadata-Version: 2.4
Name: bmsspy
Version: 2.1.1
Summary: A pure python bmssp solver for python
Author-email: Connor Makowski <conmak@mit.edu>
Project-URL: Homepage, https://github.com/connor-makowski/bmsspy
Project-URL: Bug Tracker, https://github.com/connor-makowski/bmsspy/issues
Project-URL: Documentation, https://connor-makowski.github.io/bmsspy/bmsspy.html
Classifier: Programming Language :: Python :: 3
Classifier: License :: OSI Approved :: MIT License
Classifier: Operating System :: OS Independent
Requires-Python: >=3.11
License-File: LICENSE
Dynamic: license-file
